small_rl_envs/__init__.py
small_rl_envs/down_right_sparse.py
small_rl_envs/random_maze.py
small_rl_envs/rubiks_cube_classic.py
small_rl_envs/up_right_sparse.py
small_rl_envs-0.2.0.dist-info/LICENSE
small_rl_envs-0.2.0.dist-info/METADATA
small_rl_envs-0.2.0.dist-info/WHEEL
small_rl_envs-0.2.0.dist-info/top_level.txt
small_rl_envs-0.2.0.dist-info/RECORD
